{
  "uuid": "f41ac73a-0391-4b5e-9156-57583f54500a",
  "display_id": 486,
  "title": "tool_intercept: completion_note content-based heuristic for bash success (substring 'error'/'Error'/'failed') is unreliable",
  "description": "Steps to reproduce:\n1. \n\nExpected: \nActual: \n\n**Dimension:** Error Orchestration / Cognitive Readability\n\n**Location:** /home/doll/OpenClaudia/src/tool_intercept.rs lines 717-723 (completion_note for bash)\n\n**Violation:**\nformat_tool_results_xml_with_names returns a 'completion_note' telling the model that bash succeeded, suppressing the note if content contains 'error' OR 'Error' OR 'failed' (case-sensitive substring). Problems:\n1. **False negatives.** A bash command that legitimately printed the word 'Error' as part of its help text ('Usage: mytool [--error-format=json]') is marked as 'unknown outcome' even though status was zero.\n2. **False positives.** 'git reset --hard' prints nothing on success, exit code 0 — no 'error' substring, so completion_note says success. Meanwhile a pipeline like 'cmd | grep -v error' that failed outside the substring check is marked success.\n3. **The TRUE signal — the 'is_error' boolean the caller ALREADY passed** — is correctly used for status=error earlier in the function (line 697). Just use !is_error for the completion_note; stop second-guessing the exit code with text grep.\n\n**Mandated Refactor:**\n1. Replace substring check with the existing is_error flag. bash's execute_bash returns is_error = !output.status.success() already (bash/mod.rs:384). Trust it.\n2. If the current maintainer wants a 'command succeeded but stderr non-empty' hint, compute it at execute_bash (where stdout/stderr are structured) and emit it as a dedicated is_warning field — not by re-grepping the tool's output text downstream.",
  "status": "open",
  "priority": "low",
  "created_by": "lOrm",
  "created_at": "2026-04-18T00:44:56.645897981Z",
  "updated_at": "2026-04-18T00:47:50.824182640Z",
  "labels": [
    "bug",
    "qa-review-2026-04"
  ]
}